nd2k/__init__.py
nd2k/exchange.py
nd2k/main.py
nd2k/nontrade.py
nd2k/operation.py
nd2k/swap.py
nd2k/trade.py
nd2k/transaction.py
nd2k-0.9.2.dist-info/entry_points.txt
nd2k-0.9.2.dist-info/WHEEL
nd2k-0.9.2.dist-info/METADATA
nd2k-0.9.2.dist-info/RECORD
