Metadata-Version: 2.4
Name: nd2k
Version: 0.9.2
Summary: Converts NovaDAX CSV reports to formats accepted by Koinly.
Author-email: thiagoalessio <thiagoalessio@me.com>
Requires-Python: >=3.10
License-Expression: MIT
Project-URL: Source, https://github.com/thiagoalessio/nd2k
Project-URL: Tracker, https://github.com/thiagoalessio/nd2k/issues
